Metadata-Version: 2.4
Name: pypi-honeypot-project-xyz-321
Version: 0.0.6
